runtime_stats/__init__.py
runtime_stats/runtime_stats.py
runtime_stats-0.1.2.dist-info/DESCRIPTION.rst
runtime_stats-0.1.2.dist-info/METADATA
runtime_stats-0.1.2.dist-info/RECORD
runtime_stats-0.1.2.dist-info/WHEEL
runtime_stats-0.1.2.dist-info/metadata.json
runtime_stats-0.1.2.dist-info/top_level.txt
