Metadata-Version: 2.0
Name: runtime-stats
Version: 0.1.2
Summary: Python decorator function to track runtime stats on function calls
Home-page: http://www.github.com/gstaubli/runtime_stats
Author: Garren Staubli
Author-email: gstaubli@gmail.com
License: UNKNOWN
Platform: UNKNOWN
Requires-Dist: decorator
